flask_unity/__init__.py
flask_unity/_log.py
flask_unity/api.py
flask_unity/base.py
flask_unity/blueprint.py
flask_unity/database.py
flask_unity/utils.py
flask_unity/auth/__init__.py
flask_unity/auth/admin.py
flask_unity/auth/forms.py
flask_unity/auth/models.py
flask_unity/auth/routes.py
flask_unity/cli/__init__.py
flask_unity/contrib/__init__.py
flask_unity/mute/__init__.py
flask_unity/mute/app.py
flask_unity/mute/db.py
flask_unity/mute/page.py
flask_unity/mute/project.py
flask_unity/static/do_nothing.txt
flask_unity/static/default_style/css/style.css
flask_unity/static/default_style/js/index.js
flask_unity/static/default_style/media/default_img.png
flask_unity/static/default_style/media/favicon.ico
flask_unity/static/default_style/media/logo.png
flask_unity/templates/default_errors/error_page.html
flask_unity/templates/default_page/admin_change_password.html
flask_unity/templates/default_page/admin_change_profile_image.html
flask_unity/templates/default_page/admin_login.html
flask_unity/templates/default_page/admin_register.html
flask_unity/templates/default_page/default.html
flask_unity/templates/default_page/default_base.html
flask_unity/templates/default_page/default_index.html
flask_unity-0.0.17.dist-info/LICENSE
flask_unity-0.0.17.dist-info/METADATA
flask_unity-0.0.17.dist-info/WHEEL
flask_unity-0.0.17.dist-info/entry_points.txt
flask_unity-0.0.17.dist-info/top_level.txt
flask_unity-0.0.17.dist-info/RECORD
