Metadata-Version: 2.1
Name: flask-unity
Version: 0.0.17
Summary: An extension of flask web framework that erase the complexity of structuring flask project blueprint, packages, connecting other flask extensions, database migrations, and other annoying stuffs.
Home-page: https://flask-unity.readthedocs.io
Author: Usman Musa
Author-email: usmanmusa1920@gmail.com
License: MIT
Download-URL: https://pypi.org/project/flask-unity
Project-URL: Documentation, https://flask-unity.readthedocs.io
Project-URL: Source, https://github.com/usmanmusa1920/flask-unity
Keywords: flask_unity
Platform: any
Classifier: Development Status :: 5 - Production/Stable
Classifier: Environment :: Web Environment
Classifier: Intended Audience :: Developers
Classifier: License :: OSI Approved :: MIT License
Classifier: Natural Language :: English
Classifier: Operating System :: OS Independent
Classifier: Programming Language :: Python
Classifier: Programming Language :: Python :: 3
Classifier: Programming Language :: Python :: 3.7
Classifier: Programming Language :: Python :: 3.8
Classifier: Programming Language :: Python :: 3.9
Classifier: Programming Language :: Python :: 3.10
Classifier: Framework :: Flask
Classifier: Topic :: Internet
Classifier: Topic :: Software Development :: Libraries :: Python Modules
Requires-Python: >=3.6
License-File: LICENSE
Requires-Dist: Flask-Admin >=1.6.0
Requires-Dist: Flask-Bcrypt >=1.0.1
Requires-Dist: Flask-Login >=0.6.2
Requires-Dist: Flask-SQLAlchemy >=3.0.3
Requires-Dist: Flask-WTF >=1.1.1
Requires-Dist: Flask >=2.2.3
Requires-Dist: Jinja2 >=3.1.2
Requires-Dist: Mako >=1.2.4
Requires-Dist: MarkupSafe >=2.1.2
Requires-Dist: SQLAlchemy >=1.4.45
Requires-Dist: WTForms >=3.0.1
Requires-Dist: Werkzeug >=2.2.3
Requires-Dist: alembic >=1.9.4
Requires-Dist: bcrypt >=4.0.1
Requires-Dist: click >=8.1.3
Requires-Dist: dnspython >=2.3.0
Requires-Dist: email-validator >=1.3.1
Requires-Dist: greenlet >=2.0.2
Requires-Dist: idna >=3.4
Requires-Dist: importlib-metadata >=6.0.0
Requires-Dist: itsdangerous ==2.1.2
Requires-Dist: typing-extensions >=4.5.0
Requires-Dist: zipp >=3.13.0
